mnamer/__init__.py
mnamer/__main__.py
mnamer/__version__.py
mnamer/argument.py
mnamer/const.py
mnamer/endpoints.py
mnamer/exceptions.py
mnamer/frontends.py
mnamer/language.py
mnamer/metadata.py
mnamer/providers.py
mnamer/py.typed
mnamer/setting_spec.py
mnamer/setting_store.py
mnamer/target.py
mnamer/tty.py
mnamer/types.py
mnamer/utils.py
mnamer-2.5.5.dist-info/LICENSE.txt
mnamer-2.5.5.dist-info/METADATA
mnamer-2.5.5.dist-info/WHEEL
mnamer-2.5.5.dist-info/entry_points.txt
mnamer-2.5.5.dist-info/top_level.txt
mnamer-2.5.5.dist-info/RECORD
