Metadata-Version: 2.1
Name: mnamer
Version: 2.5.5
Summary: A command-line utility for organizing media files.
Author-email: Jessy Williams <jessy@jessywilliams.com>
Maintainer-email: Jessy Williams <jessy@jessywilliams.com>
License: MIT License
Project-URL: repository, https://github.com/jkwill87/mnamer
Requires-Python: >=3.10
License-File: LICENSE.txt
Requires-Dist: appdirs (~=1.4.4)
Requires-Dist: babelfish (~=0.6.0)
Requires-Dist: guessit (~=3.7.1)
Requires-Dist: requests (==2.*)
Requires-Dist: requests-cache (~=0.9.7)
Requires-Dist: setuptools-scm (~=7.1.0)
Requires-Dist: teletype (~=1.3.4)
Requires-Dist: typing-extensions (~=4.7.1)
Provides-Extra: dev
Requires-Dist: black (~=23.7.0) ; extra == 'dev'
Requires-Dist: build (~=0.10.0) ; extra == 'dev'
Requires-Dist: codecov (~=2.1.13) ; extra == 'dev'
Requires-Dist: isort (~=5.11.4) ; extra == 'dev'
Requires-Dist: mypy (~=0.991) ; extra == 'dev'
Requires-Dist: pyflakes (~=3.0.1) ; extra == 'dev'
Requires-Dist: pylint (~=2.15.10) ; extra == 'dev'
Requires-Dist: pytest (~=7.4.0) ; extra == 'dev'
Requires-Dist: pytest-cov (~=4.1.0) ; extra == 'dev'
Requires-Dist: pytest-rerunfailures (~=12.0) ; extra == 'dev'
Requires-Dist: setuptools (~=68.1.0) ; extra == 'dev'
Requires-Dist: twine (~=4.0.2) ; extra == 'dev'
Requires-Dist: types-requests (~=2.28) ; extra == 'dev'
Requires-Dist: wheel (~=0.38.4) ; extra == 'dev'
